neurencoding/__init__.py
neurencoding/_models.py
neurencoding/design_matrix.py
neurencoding/linear.py
neurencoding/poisson.py
neurencoding/utils.py
neurencoding-0.1.8.dist-info/LICENSE
neurencoding-0.1.8.dist-info/METADATA
neurencoding-0.1.8.dist-info/WHEEL
neurencoding-0.1.8.dist-info/top_level.txt
neurencoding-0.1.8.dist-info/RECORD
