Metadata-Version: 2.1
Name: neurencoding
Version: 0.1.8
Summary: Neural encoding models made easy. Describe neuronal activity as a function of other variables
Author-email: Berk Gercek <berkgercek@duck.com>
Project-URL: Homepage, https://github.com/berkgercek/neurencoding
Project-URL: Bug Tracker, https://github.com/berkgercek/neurencoding/issues
Classifier: Intended Audience :: Science/Research
Classifier: License :: OSI Approved :: MIT License
Classifier: Operating System :: OS Independent
Classifier: Programming Language :: Python :: 3
Classifier: Topic :: Scientific/Engineering :: Bio-Informatics
Requires-Python: >=3.9
License-File: LICENSE
Requires-Dist: numpy
Requires-Dist: scipy
Requires-Dist: pandas
Requires-Dist: scikit-learn
Requires-Dist: tqdm
Requires-Dist: matplotlib
Requires-Dist: seaborn
Requires-Dist: numba
